lacroix/__init__.py
lacroix/_lib.py
lacroix/colors.json
lacroix/__pycache__/__init__.cpython-37.pyc
lacroix/__pycache__/_lib.cpython-37.pyc
lacroix-0.0.3.dist-info/LICENSE
lacroix-0.0.3.dist-info/METADATA
lacroix-0.0.3.dist-info/WHEEL
lacroix-0.0.3.dist-info/top_level.txt
lacroix-0.0.3.dist-info/RECORD
